trelliswork/__init__.py
trelliswork/compiler/translator.py
trelliswork/compiler/translators/__init__.py
trelliswork/compiler/translators/auto_shadow.py
trelliswork/compiler/translators/auto_split_pillar.py
trelliswork/compiler/translators/imports.py
trelliswork/compiler/translators/resolve_alias_of_color.py
trelliswork/compiler/translators/resolve_var_bounds.py
trelliswork/renderer/__init__.py
trelliswork/renderer/features/__init__.py
trelliswork/renderer/features/canvas.py
trelliswork/renderer/features/cards.py
trelliswork/renderer/features/line_tapes.py
trelliswork/renderer/features/pillars.py
trelliswork/renderer/features/rectangles.py
trelliswork/renderer/features/ruler.py
trelliswork/renderer/features/shadow_of_cards.py
trelliswork/renderer/features/shadow_of_line_tapes.py
trelliswork/renderer/features/shadow_of_terminals.py
trelliswork/renderer/features/terminals.py
trelliswork/renderer/features/xl_text.py
trelliswork/shared_models/__init__.py
trelliswork/shared_models/depth110/__init__.py
trelliswork/shared_models/depth110/color_system.py
trelliswork/shared_models/depth110/file_path.py
trelliswork/shared_models/depth110/point.py
trelliswork/shared_models/depth110/share.py
trelliswork/shared_models/depth110/web_safe_color.py
trelliswork/shared_models/depth110/xl_alignment.py
trelliswork/shared_models/depth120/__init__.py
trelliswork/shared_models/depth120/innings_pitched.py
trelliswork/shared_models/depth120/rectangle.py
trelliswork/shared_models/depth120/var_color.py
trelliswork/shared_models/depth130/__init__.py
trelliswork/shared_models/depth130/var_rectangle.py
trelliswork/shared_models/depth130/xl_font.py
trelliswork/shared_models/depth140/__init__.py
trelliswork/shared_models/depth140/canvas.py
trelliswork/shared_models/depth150/__init__.py
trelliswork/shared_models/depth150/card.py
trelliswork/shared_models/depth150/pillar.py
trelliswork/shared_models/depth150/terminal.py
trelliswork-10002.0.1.dist-info/METADATA
trelliswork-10002.0.1.dist-info/WHEEL
trelliswork-10002.0.1.dist-info/licenses/LICENSE
trelliswork-10002.0.1.dist-info/RECORD
