Metadata-Version: 2.4
Name: trelliswork
Version: 10002.0.1
Summary: A tool to draw graphs using Excel as a display.
Project-URL: Repository, https://github.com/muzudho/trelliswork.git
Author-email: Takahashi Satoshi <muzudho1@gmail.com>
Maintainer-email: Takahashi Satoshi <muzudho1@gmail.com>
License-Expression: MIT
License-File: LICENSE
Keywords: console application,excel
Classifier: Programming Language :: Python
Requires-Python: >=3.12.3
Requires-Dist: openpyxl>=3.1.5
Requires-Dist: tomlkit>=0.13.2
